{
  "kind": "collectionType",
  "collectionName": "our_blogs",
  "info": {
    "singularName": "our-blog",
    "pluralName": "our-blogs",
    "displayName": "blog",
    "description": ""
  },
  "options": {
    "draftAndPublish": true
  },
  "pluginOptions": {},
  "attributes": {
    "title": {
      "type": "string"
    },
    "author": {
      "type": "string"
    },
    "blogImg": {
      "type": "media",
      "multiple": true,
      "required": false,
      "allowedTypes": [
        "images",
        "videos",
        "audios",
        "files"
      ]
    },
    "date": {
      "type": "date"
    },
    "authorImg": {
      "type": "media",
      "multiple": false,
      "required": false,
      "allowedTypes": [
        "images",
        "files",
        "videos",
        "audios"
      ]
    },
    "metaTitle": {
      "type": "text"
    },
    "Note": {
      "type": "blocks"
    }
  }
}
